errorhandling/__init__.py
errorhandling/_mod.py
errorhandling/py.typed
errorhandling-2.0.1.dist-info/LICENSE
errorhandling-2.0.1.dist-info/METADATA
errorhandling-2.0.1.dist-info/WHEEL
errorhandling-2.0.1.dist-info/RECORD
